umonitor/__init__.py
umonitor/__main__.py
umonitor/uMonitor.py
umonitor-0.1.5.dist-info/LICENSE
umonitor-0.1.5.dist-info/WHEEL
umonitor-0.1.5.dist-info/METADATA
umonitor-0.1.5.dist-info/RECORD
